fyuneru/__init__.py
fyuneru/distask.py
fyuneru/geometry3d.py
fyuneru/http_utils.py
fyuneru/labelme_adapter.py
fyuneru/lib.py
fyuneru/molar_client.py
fyuneru/molar_export.py
fyuneru/molar_import.py
fyuneru/nuscenes_adapter.py
fyuneru/pcd_toolkit.py
fyuneru/redis.py
fyuneru-0.5.10.dist-info/METADATA
fyuneru-0.5.10.dist-info/WHEEL
fyuneru-0.5.10.dist-info/top_level.txt
fyuneru-0.5.10.dist-info/RECORD
